{
  "name": "Kristijan Rosandić ~ Kiki",
  "version": "2002.5.8",
  "description": "Vue.js enthusiast",
  "homepage": "Happening.xyz",
  "keywords": [
    "Problem solving",
    "Web development",
    "UI and UX"
  ],
  "engines": {
    "html": "5",
    "css": "3",
    "typescript": "*",
    "javascript": ">=ES6",
    "kotlin": ">=2",
    "c#": ">=10",
    "c++": ">=11",
    "python": "3.x",
    "java": "~11",
    "t-sql": "*"
  },
  "dependencies": {
    "vue": "3.x",
    "vite": "latest",
    "express": "latest",
    "dotnet": ">=6"
  },
  "devDependencies": {
    "os": "win11|ubuntuWSL",
    "ide": "intellij|vs",
    "editor": "vsc",
    "browser": "chrome",
    "music": "kyle-landry",
    "game": "smite|world-of-warships"
  },
  "workspaces": [
    "Google Cloud Platform",
    "Microsoft Azure",
    "Cloudflare"
  ]
}